{
    "id": "AST_LAYOUT_TYPE_TRACK",
    "is_mother": true,
    "generate_name": "track",
    "text": {
        "EN": [
            "track"
        ],
        "FA": [
            "ترک فیلم"
        ]
    },
    "attributes": [
        {
            "id": "AST_LAYOUT_ATTRIBUTE_TYPE_DEFAULT",
            "parent_element": "track",
            "generate_name": "default",
            "type": "AST_TYPE_BOOLEAN",
            "text": {
                "EN": [
                    "default"
                ],
                "FA": [
                    "پیشفرض"
                ]
            },
            "is_required": false,
            "reserved_values": []
        },
        {
            "id": "AST_LAYOUT_ATTRIBUTE_TYPE_LABEL",
            "parent_element": "track",
            "generate_name": "label",
            "type": "AST_TYPE_ANY",
            "text": {
                "EN": [
                    "label"
                ],
                "FA": [
                    "لیبل"
                ]
            },
            "is_required": false,
            "reserved_values": []
        },
        {
            "id": "AST_LAYOUT_ATTRIBUTE_TYPE_SRC",
            "parent_element": "track",
            "generate_name": "src",
            "type": "AST_TYPE_URL",
            "text": {
                "EN": [
                    "source"
                ],
                "FA": [
                    "منبع"
                ]
            },
            "is_required": false,
            "reserved_values": []
        },
        {
            "id": "AST_LAYOUT_ATTRIBUTE_TYPE_SRCLANG",
            "parent_element": "track",
            "generate_name": "srclang",
            "type": "AST_TYPE_STRING",
            "text": {
                "EN": [
                    "language"
                ],
                "FA": [
                    "زبان"
                ]
            },
            "is_required": false,
            "reserved_values": [
                {
                    "id": "AST_LAYOUT_ATTRIBUTE_VALUE_TYPE_AB",
                    "generate_name": "AB",
                    "text": {
                        "EN": [
                            "abkhazian",
                            "ab"
                        ],
                        "FA": [
                            "abkhazian",
                            "ab"
                        ]
                    }
                },
                {
                    "id": "AST_LAYOUT_ATTRIBUTE_VALUE_TYPE_AA",
                    "generate_name": "AA",
                    "text": {
                        "EN": [
                            "afar",
                            "aa"
                        ],
                        "FA": [
                            "afar",
                            "aa"
                        ]
                    }
                },
                {
                    "id": "AST_LAYOUT_ATTRIBUTE_VALUE_TYPE_AF",
                    "generate_name": "AF",
                    "text": {
                        "EN": [
                            "afrikaans",
                            "af"
                        ],
                        "FA": [
                            "afrikaans",
                            "af"
                        ]
                    }
                },
                {
                    "id": "AST_LAYOUT_ATTRIBUTE_VALUE_TYPE_AK",
                    "generate_name": "AK",
                    "text": {
                        "EN": [
                            "akan",
                            "ak"
                        ],
                        "FA": [
                            "akan",
                            "ak"
                        ]
                    }
                },
                {
                    "id": "AST_LAYOUT_ATTRIBUTE_VALUE_TYPE_SQ",
                    "generate_name": "SQ",
                    "text": {
                        "EN": [
                            "albanian",
                            "sq"
                        ],
                        "FA": [
                            "albanian",
                            "sq"
                        ]
                    }
                },
                {
                    "id": "AST_LAYOUT_ATTRIBUTE_VALUE_TYPE_AM",
                    "generate_name": "AM",
                    "text": {
                        "EN": [
                            "amharic",
                            "am"
                        ],
                        "FA": [
                            "amharic",
                            "am"
                        ]
                    }
                },
                {
                    "id": "AST_LAYOUT_ATTRIBUTE_VALUE_TYPE_AR",
                    "generate_name": "AR",
                    "text": {
                        "EN": [
                            "arabic",
                            "ar"
                        ],
                        "FA": [
                            "arabic",
                            "ar"
                        ]
                    }
                },
                {
                    "id": "AST_LAYOUT_ATTRIBUTE_VALUE_TYPE_AN",
                    "generate_name": "AN",
                    "text": {
                        "EN": [
                            "aragonese",
                            "an"
                        ],
                        "FA": [
                            "aragonese",
                            "an"
                        ]
                    }
                },
                {
                    "id": "AST_LAYOUT_ATTRIBUTE_VALUE_TYPE_HY",
                    "generate_name": "HY",
                    "text": {
                        "EN": [
                            "armenian",
                            "hy"
                        ],
                        "FA": [
                            "armenian",
                            "hy"
                        ]
                    }
                },
                {
                    "id": "AST_LAYOUT_ATTRIBUTE_VALUE_TYPE_AS",
                    "generate_name": "AS",
                    "text": {
                        "EN": [
                            "assamese",
                            "as"
                        ],
                        "FA": [
                            "assamese",
                            "as"
                        ]
                    }
                },
                {
                    "id": "AST_LAYOUT_ATTRIBUTE_VALUE_TYPE_AV",
                    "generate_name": "AV",
                    "text": {
                        "EN": [
                            "avaric",
                            "av"
                        ],
                        "FA": [
                            "avaric",
                            "av"
                        ]
                    }
                },
                {
                    "id": "AST_LAYOUT_ATTRIBUTE_VALUE_TYPE_AE",
                    "generate_name": "AE",
                    "text": {
                        "EN": [
                            "avestan",
                            "ae"
                        ],
                        "FA": [
                            "avestan",
                            "ae"
                        ]
                    }
                },
                {
                    "id": "AST_LAYOUT_ATTRIBUTE_VALUE_TYPE_AY",
                    "generate_name": "AY",
                    "text": {
                        "EN": [
                            "aymara",
                            "ay"
                        ],
                        "FA": [
                            "aymara",
                            "ay"
                        ]
                    }
                },
                {
                    "id": "AST_LAYOUT_ATTRIBUTE_VALUE_TYPE_AZ",
                    "generate_name": "AZ",
                    "text": {
                        "EN": [
                            "azerbaijani",
                            "az"
                        ],
                        "FA": [
                            "azerbaijani",
                            "az"
                        ]
                    }
                },
                {
                    "id": "AST_LAYOUT_ATTRIBUTE_VALUE_TYPE_BM",
                    "generate_name": "BM",
                    "text": {
                        "EN": [
                            "bambara",
                            "bm"
                        ],
                        "FA": [
                            "bambara",
                            "bm"
                        ]
                    }
                },
                {
                    "id": "AST_LAYOUT_ATTRIBUTE_VALUE_TYPE_BA",
                    "generate_name": "BA",
                    "text": {
                        "EN": [
                            "bashkir",
                            "ba"
                        ],
                        "FA": [
                            "bashkir",
                            "ba"
                        ]
                    }
                },
                {
                    "id": "AST_LAYOUT_ATTRIBUTE_VALUE_TYPE_EU",
                    "generate_name": "EU",
                    "text": {
                        "EN": [
                            "basque",
                            "eu"
                        ],
                        "FA": [
                            "basque",
                            "eu"
                        ]
                    }
                },
                {
                    "id": "AST_LAYOUT_ATTRIBUTE_VALUE_TYPE_BE",
                    "generate_name": "BE",
                    "text": {
                        "EN": [
                            "belarusian",
                            "be"
                        ],
                        "FA": [
                            "belarusian",
                            "be"
                        ]
                    }
                },
                {
                    "id": "AST_LAYOUT_ATTRIBUTE_VALUE_TYPE_BN",
                    "generate_name": "BN",
                    "text": {
                        "EN": [
                            "bengali",
                            "bn"
                        ],
                        "FA": [
                            "bengali",
                            "bn"
                        ]
                    }
                },
                {
                    "id": "AST_LAYOUT_ATTRIBUTE_VALUE_TYPE_BN",
                    "generate_name": "BN",
                    "text": {
                        "EN": [
                            "bangla",
                            "bn"
                        ],
                        "FA": [
                            "bangla",
                            "bn"
                        ]
                    }
                },
                {
                    "id": "AST_LAYOUT_ATTRIBUTE_VALUE_TYPE_BH",
                    "generate_name": "BH",
                    "text": {
                        "EN": [
                            "bihari",
                            "bh"
                        ],
                        "FA": [
                            "bihari",
                            "bh"
                        ]
                    }
                },
                {
                    "id": "AST_LAYOUT_ATTRIBUTE_VALUE_TYPE_BI",
                    "generate_name": "BI",
                    "text": {
                        "EN": [
                            "bislama",
                            "bi"
                        ],
                        "FA": [
                            "bislama",
                            "bi"
                        ]
                    }
                },
                {
                    "id": "AST_LAYOUT_ATTRIBUTE_VALUE_TYPE_BS",
                    "generate_name": "BS",
                    "text": {
                        "EN": [
                            "bosnian",
                            "bs"
                        ],
                        "FA": [
                            "bosnian",
                            "bs"
                        ]
                    }
                },
                {
                    "id": "AST_LAYOUT_ATTRIBUTE_VALUE_TYPE_BR",
                    "generate_name": "BR",
                    "text": {
                        "EN": [
                            "breton",
                            "br"
                        ],
                        "FA": [
                            "breton",
                            "br"
                        ]
                    }
                },
                {
                    "id": "AST_LAYOUT_ATTRIBUTE_VALUE_TYPE_BG",
                    "generate_name": "BG",
                    "text": {
                        "EN": [
                            "bulgarian",
                            "bg"
                        ],
                        "FA": [
                            "bulgarian",
                            "bg"
                        ]
                    }
                },
                {
                    "id": "AST_LAYOUT_ATTRIBUTE_VALUE_TYPE_MY",
                    "generate_name": "MY",
                    "text": {
                        "EN": [
                            "burmese",
                            "my"
                        ],
                        "FA": [
                            "burmese",
                            "my"
                        ]
                    }
                },
                {
                    "id": "AST_LAYOUT_ATTRIBUTE_VALUE_TYPE_CA",
                    "generate_name": "CA",
                    "text": {
                        "EN": [
                            "catalan",
                            "ca"
                        ],
                        "FA": [
                            "catalan",
                            "ca"
                        ]
                    }
                },
                {
                    "id": "AST_LAYOUT_ATTRIBUTE_VALUE_TYPE_CH",
                    "generate_name": "CH",
                    "text": {
                        "EN": [
                            "chamorro",
                            "ch"
                        ],
                        "FA": [
                            "chamorro",
                            "ch"
                        ]
                    }
                },
                {
                    "id": "AST_LAYOUT_ATTRIBUTE_VALUE_TYPE_CE",
                    "generate_name": "CE",
                    "text": {
                        "EN": [
                            "chechen",
                            "ce"
                        ],
                        "FA": [
                            "chechen",
                            "ce"
                        ]
                    }
                },
                {
                    "id": "AST_LAYOUT_ATTRIBUTE_VALUE_TYPE_NY",
                    "generate_name": "NY",
                    "text": {
                        "EN": [
                            "chichewa, chewa, nyanja",
                            "ny"
                        ],
                        "FA": [
                            "chichewa, chewa, nyanja",
                            "ny"
                        ]
                    }
                },
                {
                    "id": "AST_LAYOUT_ATTRIBUTE_VALUE_TYPE_ZH",
                    "generate_name": "ZH",
                    "text": {
                        "EN": [
                            "chinese",
                            "zh"
                        ],
                        "FA": [
                            "chinese",
                            "zh"
                        ]
                    }
                },
                {
                    "id": "AST_LAYOUT_ATTRIBUTE_VALUE_TYPE_ZH_HANS",
                    "generate_name": "ZH-HANS",
                    "text": {
                        "EN": [
                            "chinese simplified",
                            "zh-hans"
                        ],
                        "FA": [
                            "chinese simplified",
                            "zh-hans"
                        ]
                    }
                },
                {
                    "id": "AST_LAYOUT_ATTRIBUTE_VALUE_TYPE_ZH_HANT",
                    "generate_name": "ZH-HANT",
                    "text": {
                        "EN": [
                            "chinese traditional",
                            "zh-hant"
                        ],
                        "FA": [
                            "chinese traditional",
                            "zh-hant"
                        ]
                    }
                },
                {
                    "id": "AST_LAYOUT_ATTRIBUTE_VALUE_TYPE_CV",
                    "generate_name": "CV",
                    "text": {
                        "EN": [
                            "chuvash",
                            "cv"
                        ],
                        "FA": [
                            "chuvash",
                            "cv"
                        ]
                    }
                },
                {
                    "id": "AST_LAYOUT_ATTRIBUTE_VALUE_TYPE_KW",
                    "generate_name": "KW",
                    "text": {
                        "EN": [
                            "cornish",
                            "kw"
                        ],
                        "FA": [
                            "cornish",
                            "kw"
                        ]
                    }
                },
                {
                    "id": "AST_LAYOUT_ATTRIBUTE_VALUE_TYPE_CO",
                    "generate_name": "CO",
                    "text": {
                        "EN": [
                            "corsican",
                            "co"
                        ],
                        "FA": [
                            "corsican",
                            "co"
                        ]
                    }
                },
                {
                    "id": "AST_LAYOUT_ATTRIBUTE_VALUE_TYPE_CR",
                    "generate_name": "CR",
                    "text": {
                        "EN": [
                            "cree",
                            "cr"
                        ],
                        "FA": [
                            "cree",
                            "cr"
                        ]
                    }
                },
                {
                    "id": "AST_LAYOUT_ATTRIBUTE_VALUE_TYPE_HR",
                    "generate_name": "HR",
                    "text": {
                        "EN": [
                            "croatian",
                            "hr"
                        ],
                        "FA": [
                            "croatian",
                            "hr"
                        ]
                    }
                },
                {
                    "id": "AST_LAYOUT_ATTRIBUTE_VALUE_TYPE_CS",
                    "generate_name": "CS",
                    "text": {
                        "EN": [
                            "czech",
                            "cs"
                        ],
                        "FA": [
                            "czech",
                            "cs"
                        ]
                    }
                },
                {
                    "id": "AST_LAYOUT_ATTRIBUTE_VALUE_TYPE_DA",
                    "generate_name": "DA",
                    "text": {
                        "EN": [
                            "danish",
                            "da"
                        ],
                        "FA": [
                            "danish",
                            "da"
                        ]
                    }
                },
                {
                    "id": "AST_LAYOUT_ATTRIBUTE_VALUE_TYPE_DV",
                    "generate_name": "DV",
                    "text": {
                        "EN": [
                            "divehi",
                            "dv"
                        ],
                        "FA": [
                            "divehi",
                            "dv"
                        ]
                    }
                },
                {
                    "id": "AST_LAYOUT_ATTRIBUTE_VALUE_TYPE_DV",
                    "generate_name": "DV",
                    "text": {
                        "EN": [
                            "dhivehi",
                            "dv"
                        ],
                        "FA": [
                            "dhivehi",
                            "dv"
                        ]
                    }
                },
                {
                    "id": "AST_LAYOUT_ATTRIBUTE_VALUE_TYPE_DV",
                    "generate_name": "DV",
                    "text": {
                        "EN": [
                            "maldivian",
                            "dv"
                        ],
                        "FA": [
                            "maldivian",
                            "dv"
                        ]
                    }
                },
                {
                    "id": "AST_LAYOUT_ATTRIBUTE_VALUE_TYPE_NL",
                    "generate_name": "NL",
                    "text": {
                        "EN": [
                            "dutch",
                            "nl"
                        ],
                        "FA": [
                            "dutch",
                            "nl"
                        ]
                    }
                },
                {
                    "id": "AST_LAYOUT_ATTRIBUTE_VALUE_TYPE_DZ",
                    "generate_name": "DZ",
                    "text": {
                        "EN": [
                            "dzongkha",
                            "dz"
                        ],
                        "FA": [
                            "dzongkha",
                            "dz"
                        ]
                    }
                },
                {
                    "id": "AST_LAYOUT_ATTRIBUTE_VALUE_TYPE_EN",
                    "generate_name": "EN",
                    "text": {
                        "EN": [
                            "english",
                            "en"
                        ],
                        "FA": [
                            "english",
                            "en"
                        ]
                    }
                },
                {
                    "id": "AST_LAYOUT_ATTRIBUTE_VALUE_TYPE_EO",
                    "generate_name": "EO",
                    "text": {
                        "EN": [
                            "esperanto",
                            "eo"
                        ],
                        "FA": [
                            "esperanto",
                            "eo"
                        ]
                    }
                },
                {
                    "id": "AST_LAYOUT_ATTRIBUTE_VALUE_TYPE_ET",
                    "generate_name": "ET",
                    "text": {
                        "EN": [
                            "estonian",
                            "et"
                        ],
                        "FA": [
                            "estonian",
                            "et"
                        ]
                    }
                },
                {
                    "id": "AST_LAYOUT_ATTRIBUTE_VALUE_TYPE_EE",
                    "generate_name": "EE",
                    "text": {
                        "EN": [
                            "ewe",
                            "ee"
                        ],
                        "FA": [
                            "ewe",
                            "ee"
                        ]
                    }
                },
                {
                    "id": "AST_LAYOUT_ATTRIBUTE_VALUE_TYPE_FO",
                    "generate_name": "FO",
                    "text": {
                        "EN": [
                            "faroese",
                            "fo"
                        ],
                        "FA": [
                            "faroese",
                            "fo"
                        ]
                    }
                },
                {
                    "id": "AST_LAYOUT_ATTRIBUTE_VALUE_TYPE_FJ",
                    "generate_name": "FJ",
                    "text": {
                        "EN": [
                            "fijian",
                            "fj"
                        ],
                        "FA": [
                            "fijian",
                            "fj"
                        ]
                    }
                },
                {
                    "id": "AST_LAYOUT_ATTRIBUTE_VALUE_TYPE_FI",
                    "generate_name": "FI",
                    "text": {
                        "EN": [
                            "finnish",
                            "fi"
                        ],
                        "FA": [
                            "finnish",
                            "fi"
                        ]
                    }
                },
                {
                    "id": "AST_LAYOUT_ATTRIBUTE_VALUE_TYPE_FR",
                    "generate_name": "FR",
                    "text": {
                        "EN": [
                            "french",
                            "fr"
                        ],
                        "FA": [
                            "french",
                            "fr"
                        ]
                    }
                },
                {
                    "id": "AST_LAYOUT_ATTRIBUTE_VALUE_TYPE_FF",
                    "generate_name": "FF",
                    "text": {
                        "EN": [
                            "fula, fulah, pulaar, pular",
                            "ff"
                        ],
                        "FA": [
                            "fula, fulah, pulaar, pular",
                            "ff"
                        ]
                    }
                },
                {
                    "id": "AST_LAYOUT_ATTRIBUTE_VALUE_TYPE_GL",
                    "generate_name": "GL",
                    "text": {
                        "EN": [
                            "galician",
                            "gl"
                        ],
                        "FA": [
                            "galician",
                            "gl"
                        ]
                    }
                },
                {
                    "id": "AST_LAYOUT_ATTRIBUTE_VALUE_TYPE_GD",
                    "generate_name": "GD",
                    "text": {
                        "EN": [
                            "gaelic scottish",
                            "gd"
                        ],
                        "FA": [
                            "gaelic scottish",
                            "gd"
                        ]
                    }
                },
                {
                    "id": "AST_LAYOUT_ATTRIBUTE_VALUE_TYPE_GV",
                    "generate_name": "GV",
                    "text": {
                        "EN": [
                            "gaelic manx",
                            "gv"
                        ],
                        "FA": [
                            "gaelic manx",
                            "gv"
                        ]
                    }
                },
                {
                    "id": "AST_LAYOUT_ATTRIBUTE_VALUE_TYPE_KA",
                    "generate_name": "KA",
                    "text": {
                        "EN": [
                            "georgian",
                            "ka"
                        ],
                        "FA": [
                            "georgian",
                            "ka"
                        ]
                    }
                },
                {
                    "id": "AST_LAYOUT_ATTRIBUTE_VALUE_TYPE_DE",
                    "generate_name": "DE",
                    "text": {
                        "EN": [
                            "german",
                            "de"
                        ],
                        "FA": [
                            "german",
                            "de"
                        ]
                    }
                },
                {
                    "id": "AST_LAYOUT_ATTRIBUTE_VALUE_TYPE_EL",
                    "generate_name": "EL",
                    "text": {
                        "EN": [
                            "greek",
                            "el"
                        ],
                        "FA": [
                            "greek",
                            "el"
                        ]
                    }
                },
                {
                    "id": "AST_LAYOUT_ATTRIBUTE_VALUE_TYPE_KL",
                    "generate_name": "KL",
                    "text": {
                        "EN": [
                            "greenlandic",
                            "kl"
                        ],
                        "FA": [
                            "greenlandic",
                            "kl"
                        ]
                    }
                },
                {
                    "id": "AST_LAYOUT_ATTRIBUTE_VALUE_TYPE_GN",
                    "generate_name": "GN",
                    "text": {
                        "EN": [
                            "guarani",
                            "gn"
                        ],
                        "FA": [
                            "guarani",
                            "gn"
                        ]
                    }
                },
                {
                    "id": "AST_LAYOUT_ATTRIBUTE_VALUE_TYPE_GU",
                    "generate_name": "GU",
                    "text": {
                        "EN": [
                            "gujarati",
                            "gu"
                        ],
                        "FA": [
                            "gujarati",
                            "gu"
                        ]
                    }
                },
                {
                    "id": "AST_LAYOUT_ATTRIBUTE_VALUE_TYPE_HT",
                    "generate_name": "HT",
                    "text": {
                        "EN": [
                            "haitian creole",
                            "ht"
                        ],
                        "FA": [
                            "haitian creole",
                            "ht"
                        ]
                    }
                },
                {
                    "id": "AST_LAYOUT_ATTRIBUTE_VALUE_TYPE_HA",
                    "generate_name": "HA",
                    "text": {
                        "EN": [
                            "hausa",
                            "ha"
                        ],
                        "FA": [
                            "hausa",
                            "ha"
                        ]
                    }
                },
                {
                    "id": "AST_LAYOUT_ATTRIBUTE_VALUE_TYPE_HE",
                    "generate_name": "HE",
                    "text": {
                        "EN": [
                            "hebrew",
                            "he"
                        ],
                        "FA": [
                            "hebrew",
                            "he"
                        ]
                    }
                },
                {
                    "id": "AST_LAYOUT_ATTRIBUTE_VALUE_TYPE_HZ",
                    "generate_name": "HZ",
                    "text": {
                        "EN": [
                            "herero",
                            "hz"
                        ],
                        "FA": [
                            "herero",
                            "hz"
                        ]
                    }
                },
                {
                    "id": "AST_LAYOUT_ATTRIBUTE_VALUE_TYPE_HI",
                    "generate_name": "HI",
                    "text": {
                        "EN": [
                            "hindi",
                            "hi"
                        ],
                        "FA": [
                            "hindi",
                            "hi"
                        ]
                    }
                },
                {
                    "id": "AST_LAYOUT_ATTRIBUTE_VALUE_TYPE_HO",
                    "generate_name": "HO",
                    "text": {
                        "EN": [
                            "hiri motu",
                            "ho"
                        ],
                        "FA": [
                            "hiri motu",
                            "ho"
                        ]
                    }
                },
                {
                    "id": "AST_LAYOUT_ATTRIBUTE_VALUE_TYPE_HU",
                    "generate_name": "HU",
                    "text": {
                        "EN": [
                            "hungarian",
                            "hu"
                        ],
                        "FA": [
                            "hungarian",
                            "hu"
                        ]
                    }
                },
                {
                    "id": "AST_LAYOUT_ATTRIBUTE_VALUE_TYPE_IS",
                    "generate_name": "IS",
                    "text": {
                        "EN": [
                            "icelandic",
                            "is"
                        ],
                        "FA": [
                            "icelandic",
                            "is"
                        ]
                    }
                },
                {
                    "id": "AST_LAYOUT_ATTRIBUTE_VALUE_TYPE_IO",
                    "generate_name": "IO",
                    "text": {
                        "EN": [
                            "ido",
                            "io"
                        ],
                        "FA": [
                            "ido",
                            "io"
                        ]
                    }
                },
                {
                    "id": "AST_LAYOUT_ATTRIBUTE_VALUE_TYPE_IG",
                    "generate_name": "IG",
                    "text": {
                        "EN": [
                            "igbo",
                            "ig"
                        ],
                        "FA": [
                            "igbo",
                            "ig"
                        ]
                    }
                },
                {
                    "id": "AST_LAYOUT_ATTRIBUTE_VALUE_TYPE_ID,_IN",
                    "generate_name": "ID, IN",
                    "text": {
                        "EN": [
                            "indonesian",
                            "id, in"
                        ],
                        "FA": [
                            "indonesian",
                            "id, in"
                        ]
                    }
                },
                {
                    "id": "AST_LAYOUT_ATTRIBUTE_VALUE_TYPE_IA",
                    "generate_name": "IA",
                    "text": {
                        "EN": [
                            "interlingua",
                            "ia"
                        ],
                        "FA": [
                            "interlingua",
                            "ia"
                        ]
                    }
                },
                {
                    "id": "AST_LAYOUT_ATTRIBUTE_VALUE_TYPE_IE",
                    "generate_name": "IE",
                    "text": {
                        "EN": [
                            "interlingue",
                            "ie"
                        ],
                        "FA": [
                            "interlingue",
                            "ie"
                        ]
                    }
                },
                {
                    "id": "AST_LAYOUT_ATTRIBUTE_VALUE_TYPE_IU",
                    "generate_name": "IU",
                    "text": {
                        "EN": [
                            "inuktitut",
                            "iu"
                        ],
                        "FA": [
                            "inuktitut",
                            "iu"
                        ]
                    }
                },
                {
                    "id": "AST_LAYOUT_ATTRIBUTE_VALUE_TYPE_IK",
                    "generate_name": "IK",
                    "text": {
                        "EN": [
                            "inupiak",
                            "ik"
                        ],
                        "FA": [
                            "inupiak",
                            "ik"
                        ]
                    }
                },
                {
                    "id": "AST_LAYOUT_ATTRIBUTE_VALUE_TYPE_GA",
                    "generate_name": "GA",
                    "text": {
                        "EN": [
                            "irish",
                            "ga"
                        ],
                        "FA": [
                            "irish",
                            "ga"
                        ]
                    }
                },
                {
                    "id": "AST_LAYOUT_ATTRIBUTE_VALUE_TYPE_IT",
                    "generate_name": "IT",
                    "text": {
                        "EN": [
                            "italian",
                            "it"
                        ],
                        "FA": [
                            "italian",
                            "it"
                        ]
                    }
                },
                {
                    "id": "AST_LAYOUT_ATTRIBUTE_VALUE_TYPE_JA",
                    "generate_name": "JA",
                    "text": {
                        "EN": [
                            "japanese",
                            "ja"
                        ],
                        "FA": [
                            "japanese",
                            "ja"
                        ]
                    }
                },
                {
                    "id": "AST_LAYOUT_ATTRIBUTE_VALUE_TYPE_JV",
                    "generate_name": "JV",
                    "text": {
                        "EN": [
                            "javanese",
                            "jv"
                        ],
                        "FA": [
                            "javanese",
                            "jv"
                        ]
                    }
                },
                {
                    "id": "AST_LAYOUT_ATTRIBUTE_VALUE_TYPE_KL",
                    "generate_name": "KL",
                    "text": {
                        "EN": [
                            "kalaallisut",
                            "kl"
                        ],
                        "FA": [
                            "kalaallisut",
                            "kl"
                        ]
                    }
                },
                {
                    "id": "AST_LAYOUT_ATTRIBUTE_VALUE_TYPE_KL",
                    "generate_name": "KL",
                    "text": {
                        "EN": [
                            "greenlandic",
                            "kl"
                        ],
                        "FA": [
                            "greenlandic",
                            "kl"
                        ]
                    }
                },
                {
                    "id": "AST_LAYOUT_ATTRIBUTE_VALUE_TYPE_KN",
                    "generate_name": "KN",
                    "text": {
                        "EN": [
                            "kannada",
                            "kn"
                        ],
                        "FA": [
                            "kannada",
                            "kn"
                        ]
                    }
                },
                {
                    "id": "AST_LAYOUT_ATTRIBUTE_VALUE_TYPE_KR",
                    "generate_name": "KR",
                    "text": {
                        "EN": [
                            "kanuri",
                            "kr"
                        ],
                        "FA": [
                            "kanuri",
                            "kr"
                        ]
                    }
                },
                {
                    "id": "AST_LAYOUT_ATTRIBUTE_VALUE_TYPE_KS",
                    "generate_name": "KS",
                    "text": {
                        "EN": [
                            "kashmiri",
                            "ks"
                        ],
                        "FA": [
                            "kashmiri",
                            "ks"
                        ]
                    }
                },
                {
                    "id": "AST_LAYOUT_ATTRIBUTE_VALUE_TYPE_KK",
                    "generate_name": "KK",
                    "text": {
                        "EN": [
                            "kazakh",
                            "kk"
                        ],
                        "FA": [
                            "kazakh",
                            "kk"
                        ]
                    }
                },
                {
                    "id": "AST_LAYOUT_ATTRIBUTE_VALUE_TYPE_KM",
                    "generate_name": "KM",
                    "text": {
                        "EN": [
                            "khmer",
                            "km"
                        ],
                        "FA": [
                            "khmer",
                            "km"
                        ]
                    }
                },
                {
                    "id": "AST_LAYOUT_ATTRIBUTE_VALUE_TYPE_KI",
                    "generate_name": "KI",
                    "text": {
                        "EN": [
                            "kikuyu",
                            "ki"
                        ],
                        "FA": [
                            "kikuyu",
                            "ki"
                        ]
                    }
                },
                {
                    "id": "AST_LAYOUT_ATTRIBUTE_VALUE_TYPE_RW",
                    "generate_name": "RW",
                    "text": {
                        "EN": [
                            "kinyarwanda rwanda",
                            "rw"
                        ],
                        "FA": [
                            "kinyarwanda rwanda",
                            "rw"
                        ]
                    }
                },
                {
                    "id": "AST_LAYOUT_ATTRIBUTE_VALUE_TYPE_RN",
                    "generate_name": "RN",
                    "text": {
                        "EN": [
                            "kirundi",
                            "rn"
                        ],
                        "FA": [
                            "kirundi",
                            "rn"
                        ]
                    }
                },
                {
                    "id": "AST_LAYOUT_ATTRIBUTE_VALUE_TYPE_KY",
                    "generate_name": "KY",
                    "text": {
                        "EN": [
                            "kyrgyz",
                            "ky"
                        ],
                        "FA": [
                            "kyrgyz",
                            "ky"
                        ]
                    }
                },
                {
                    "id": "AST_LAYOUT_ATTRIBUTE_VALUE_TYPE_KV",
                    "generate_name": "KV",
                    "text": {
                        "EN": [
                            "komi",
                            "kv"
                        ],
                        "FA": [
                            "komi",
                            "kv"
                        ]
                    }
                },
                {
                    "id": "AST_LAYOUT_ATTRIBUTE_VALUE_TYPE_KG",
                    "generate_name": "KG",
                    "text": {
                        "EN": [
                            "kongo",
                            "kg"
                        ],
                        "FA": [
                            "kongo",
                            "kg"
                        ]
                    }
                },
                {
                    "id": "AST_LAYOUT_ATTRIBUTE_VALUE_TYPE_KO",
                    "generate_name": "KO",
                    "text": {
                        "EN": [
                            "korean",
                            "ko"
                        ],
                        "FA": [
                            "korean",
                            "ko"
                        ]
                    }
                },
                {
                    "id": "AST_LAYOUT_ATTRIBUTE_VALUE_TYPE_KU",
                    "generate_name": "KU",
                    "text": {
                        "EN": [
                            "kurdish",
                            "ku"
                        ],
                        "FA": [
                            "kurdish",
                            "ku"
                        ]
                    }
                },
                {
                    "id": "AST_LAYOUT_ATTRIBUTE_VALUE_TYPE_KJ",
                    "generate_name": "KJ",
                    "text": {
                        "EN": [
                            "kwanyama",
                            "kj"
                        ],
                        "FA": [
                            "kwanyama",
                            "kj"
                        ]
                    }
                },
                {
                    "id": "AST_LAYOUT_ATTRIBUTE_VALUE_TYPE_LO",
                    "generate_name": "LO",
                    "text": {
                        "EN": [
                            "lao",
                            "lo"
                        ],
                        "FA": [
                            "lao",
                            "lo"
                        ]
                    }
                },
                {
                    "id": "AST_LAYOUT_ATTRIBUTE_VALUE_TYPE_LA",
                    "generate_name": "LA",
                    "text": {
                        "EN": [
                            "latin",
                            "la"
                        ],
                        "FA": [
                            "latin",
                            "la"
                        ]
                    }
                },
                {
                    "id": "AST_LAYOUT_ATTRIBUTE_VALUE_TYPE_LV",
                    "generate_name": "LV",
                    "text": {
                        "EN": [
                            "latvian lettish",
                            "lv"
                        ],
                        "FA": [
                            "latvian lettish",
                            "lv"
                        ]
                    }
                },
                {
                    "id": "AST_LAYOUT_ATTRIBUTE_VALUE_TYPE_LI",
                    "generate_name": "LI",
                    "text": {
                        "EN": [
                            "limburgish limburger",
                            "li"
                        ],
                        "FA": [
                            "limburgish limburger",
                            "li"
                        ]
                    }
                },
                {
                    "id": "AST_LAYOUT_ATTRIBUTE_VALUE_TYPE_LN",
                    "generate_name": "LN",
                    "text": {
                        "EN": [
                            "lingala",
                            "ln"
                        ],
                        "FA": [
                            "lingala",
                            "ln"
                        ]
                    }
                },
                {
                    "id": "AST_LAYOUT_ATTRIBUTE_VALUE_TYPE_LT",
                    "generate_name": "LT",
                    "text": {
                        "EN": [
                            "lithuanian",
                            "lt"
                        ],
                        "FA": [
                            "lithuanian",
                            "lt"
                        ]
                    }
                },
                {
                    "id": "AST_LAYOUT_ATTRIBUTE_VALUE_TYPE_LU",
                    "generate_name": "LU",
                    "text": {
                        "EN": [
                            "luga-katanga",
                            "lu"
                        ],
                        "FA": [
                            "luga-katanga",
                            "lu"
                        ]
                    }
                },
                {
                    "id": "AST_LAYOUT_ATTRIBUTE_VALUE_TYPE_LG",
                    "generate_name": "LG",
                    "text": {
                        "EN": [
                            "luganda, ganda",
                            "lg"
                        ],
                        "FA": [
                            "luganda, ganda",
                            "lg"
                        ]
                    }
                },
                {
                    "id": "AST_LAYOUT_ATTRIBUTE_VALUE_TYPE_LB",
                    "generate_name": "LB",
                    "text": {
                        "EN": [
                            "luxembourgish",
                            "lb"
                        ],
                        "FA": [
                            "luxembourgish",
                            "lb"
                        ]
                    }
                },
                {
                    "id": "AST_LAYOUT_ATTRIBUTE_VALUE_TYPE_GV",
                    "generate_name": "GV",
                    "text": {
                        "EN": [
                            "manx",
                            "gv"
                        ],
                        "FA": [
                            "manx",
                            "gv"
                        ]
                    }
                },
                {
                    "id": "AST_LAYOUT_ATTRIBUTE_VALUE_TYPE_MK",
                    "generate_name": "MK",
                    "text": {
                        "EN": [
                            "macedonian",
                            "mk"
                        ],
                        "FA": [
                            "macedonian",
                            "mk"
                        ]
                    }
                },
                {
                    "id": "AST_LAYOUT_ATTRIBUTE_VALUE_TYPE_MG",
                    "generate_name": "MG",
                    "text": {
                        "EN": [
                            "malagasy",
                            "mg"
                        ],
                        "FA": [
                            "malagasy",
                            "mg"
                        ]
                    }
                },
                {
                    "id": "AST_LAYOUT_ATTRIBUTE_VALUE_TYPE_MS",
                    "generate_name": "MS",
                    "text": {
                        "EN": [
                            "malay",
                            "ms"
                        ],
                        "FA": [
                            "malay",
                            "ms"
                        ]
                    }
                },
                {
                    "id": "AST_LAYOUT_ATTRIBUTE_VALUE_TYPE_ML",
                    "generate_name": "ML",
                    "text": {
                        "EN": [
                            "malayalam",
                            "ml"
                        ],
                        "FA": [
                            "malayalam",
                            "ml"
                        ]
                    }
                },
                {
                    "id": "AST_LAYOUT_ATTRIBUTE_VALUE_TYPE_MT",
                    "generate_name": "MT",
                    "text": {
                        "EN": [
                            "maltese",
                            "mt"
                        ],
                        "FA": [
                            "maltese",
                            "mt"
                        ]
                    }
                },
                {
                    "id": "AST_LAYOUT_ATTRIBUTE_VALUE_TYPE_MI",
                    "generate_name": "MI",
                    "text": {
                        "EN": [
                            "maori",
                            "mi"
                        ],
                        "FA": [
                            "maori",
                            "mi"
                        ]
                    }
                },
                {
                    "id": "AST_LAYOUT_ATTRIBUTE_VALUE_TYPE_MR",
                    "generate_name": "MR",
                    "text": {
                        "EN": [
                            "marathi",
                            "mr"
                        ],
                        "FA": [
                            "marathi",
                            "mr"
                        ]
                    }
                },
                {
                    "id": "AST_LAYOUT_ATTRIBUTE_VALUE_TYPE_MH",
                    "generate_name": "MH",
                    "text": {
                        "EN": [
                            "marshallese",
                            "mh"
                        ],
                        "FA": [
                            "marshallese",
                            "mh"
                        ]
                    }
                },
                {
                    "id": "AST_LAYOUT_ATTRIBUTE_VALUE_TYPE_MO",
                    "generate_name": "MO",
                    "text": {
                        "EN": [
                            "moldavian",
                            "mo"
                        ],
                        "FA": [
                            "moldavian",
                            "mo"
                        ]
                    }
                },
                {
                    "id": "AST_LAYOUT_ATTRIBUTE_VALUE_TYPE_MN",
                    "generate_name": "MN",
                    "text": {
                        "EN": [
                            "mongolian",
                            "mn"
                        ],
                        "FA": [
                            "mongolian",
                            "mn"
                        ]
                    }
                },
                {
                    "id": "AST_LAYOUT_ATTRIBUTE_VALUE_TYPE_NA",
                    "generate_name": "NA",
                    "text": {
                        "EN": [
                            "nauru",
                            "na"
                        ],
                        "FA": [
                            "nauru",
                            "na"
                        ]
                    }
                },
                {
                    "id": "AST_LAYOUT_ATTRIBUTE_VALUE_TYPE_NV",
                    "generate_name": "NV",
                    "text": {
                        "EN": [
                            "navajo",
                            "nv"
                        ],
                        "FA": [
                            "navajo",
                            "nv"
                        ]
                    }
                },
                {
                    "id": "AST_LAYOUT_ATTRIBUTE_VALUE_TYPE_NG",
                    "generate_name": "NG",
                    "text": {
                        "EN": [
                            "ndonga",
                            "ng"
                        ],
                        "FA": [
                            "ndonga",
                            "ng"
                        ]
                    }
                },
                {
                    "id": "AST_LAYOUT_ATTRIBUTE_VALUE_TYPE_ND",
                    "generate_name": "ND",
                    "text": {
                        "EN": [
                            "northern ndebele",
                            "nd"
                        ],
                        "FA": [
                            "northern ndebele",
                            "nd"
                        ]
                    }
                },
                {
                    "id": "AST_LAYOUT_ATTRIBUTE_VALUE_TYPE_NE",
                    "generate_name": "NE",
                    "text": {
                        "EN": [
                            "nepali",
                            "ne"
                        ],
                        "FA": [
                            "nepali",
                            "ne"
                        ]
                    }
                },
                {
                    "id": "AST_LAYOUT_ATTRIBUTE_VALUE_TYPE_NO",
                    "generate_name": "NO",
                    "text": {
                        "EN": [
                            "norwegian",
                            "no"
                        ],
                        "FA": [
                            "norwegian",
                            "no"
                        ]
                    }
                },
                {
                    "id": "AST_LAYOUT_ATTRIBUTE_VALUE_TYPE_NB",
                    "generate_name": "NB",
                    "text": {
                        "EN": [
                            "norwegian bokmål",
                            "nb"
                        ],
                        "FA": [
                            "norwegian bokmål",
                            "nb"
                        ]
                    }
                },
                {
                    "id": "AST_LAYOUT_ATTRIBUTE_VALUE_TYPE_NN",
                    "generate_name": "NN",
                    "text": {
                        "EN": [
                            "norwegian nynorsk",
                            "nn"
                        ],
                        "FA": [
                            "norwegian nynorsk",
                            "nn"
                        ]
                    }
                },
                {
                    "id": "AST_LAYOUT_ATTRIBUTE_VALUE_TYPE_II",
                    "generate_name": "II",
                    "text": {
                        "EN": [
                            "nuosu",
                            "ii"
                        ],
                        "FA": [
                            "nuosu",
                            "ii"
                        ]
                    }
                },
                {
                    "id": "AST_LAYOUT_ATTRIBUTE_VALUE_TYPE_OC",
                    "generate_name": "OC",
                    "text": {
                        "EN": [
                            "occitan",
                            "oc"
                        ],
                        "FA": [
                            "occitan",
                            "oc"
                        ]
                    }
                },
                {
                    "id": "AST_LAYOUT_ATTRIBUTE_VALUE_TYPE_OJ",
                    "generate_name": "OJ",
                    "text": {
                        "EN": [
                            "ojibwe",
                            "oj"
                        ],
                        "FA": [
                            "ojibwe",
                            "oj"
                        ]
                    }
                },
                {
                    "id": "AST_LAYOUT_ATTRIBUTE_VALUE_TYPE_CU",
                    "generate_name": "CU",
                    "text": {
                        "EN": [
                            "old church slavonic, old bulgarian",
                            "cu"
                        ],
                        "FA": [
                            "old church slavonic, old bulgarian",
                            "cu"
                        ]
                    }
                },
                {
                    "id": "AST_LAYOUT_ATTRIBUTE_VALUE_TYPE_OR",
                    "generate_name": "OR",
                    "text": {
                        "EN": [
                            "oriya",
                            "or"
                        ],
                        "FA": [
                            "oriya",
                            "or"
                        ]
                    }
                },
                {
                    "id": "AST_LAYOUT_ATTRIBUTE_VALUE_TYPE_OM",
                    "generate_name": "OM",
                    "text": {
                        "EN": [
                            "oromo afaan oromo",
                            "om"
                        ],
                        "FA": [
                            "oromo afaan oromo",
                            "om"
                        ]
                    }
                },
                {
                    "id": "AST_LAYOUT_ATTRIBUTE_VALUE_TYPE_OS",
                    "generate_name": "OS",
                    "text": {
                        "EN": [
                            "ossetian",
                            "os"
                        ],
                        "FA": [
                            "ossetian",
                            "os"
                        ]
                    }
                },
                {
                    "id": "AST_LAYOUT_ATTRIBUTE_VALUE_TYPE_PI",
                    "generate_name": "PI",
                    "text": {
                        "EN": [
                            "pāli",
                            "pi"
                        ],
                        "FA": [
                            "pāli",
                            "pi"
                        ]
                    }
                },
                {
                    "id": "AST_LAYOUT_ATTRIBUTE_VALUE_TYPE_PS",
                    "generate_name": "PS",
                    "text": {
                        "EN": [
                            "pashto, pushto",
                            "ps"
                        ],
                        "FA": [
                            "pashto, pushto",
                            "ps"
                        ]
                    }
                },
                {
                    "id": "AST_LAYOUT_ATTRIBUTE_VALUE_TYPE_FA",
                    "generate_name": "FA",
                    "text": {
                        "EN": [
                            "persian",
                            "fa"
                        ],
                        "FA": [
                            "persian",
                            "fa"
                        ]
                    }
                },
                {
                    "id": "AST_LAYOUT_ATTRIBUTE_VALUE_TYPE_FA",
                    "generate_name": "FA",
                    "text": {
                        "EN": [
                            "farsi",
                            "fa"
                        ],
                        "FA": [
                            "farsi",
                            "fa"
                        ]
                    }
                },
                {
                    "id": "AST_LAYOUT_ATTRIBUTE_VALUE_TYPE_PL",
                    "generate_name": "PL",
                    "text": {
                        "EN": [
                            "polish",
                            "pl"
                        ],
                        "FA": [
                            "polish",
                            "pl"
                        ]
                    }
                },
                {
                    "id": "AST_LAYOUT_ATTRIBUTE_VALUE_TYPE_PT",
                    "generate_name": "PT",
                    "text": {
                        "EN": [
                            "portuguese",
                            "pt"
                        ],
                        "FA": [
                            "portuguese",
                            "pt"
                        ]
                    }
                },
                {
                    "id": "AST_LAYOUT_ATTRIBUTE_VALUE_TYPE_PA",
                    "generate_name": "PA",
                    "text": {
                        "EN": [
                            "punjabi",
                            "pa"
                        ],
                        "FA": [
                            "punjabi",
                            "pa"
                        ]
                    }
                },
                {
                    "id": "AST_LAYOUT_ATTRIBUTE_VALUE_TYPE_PA",
                    "generate_name": "PA",
                    "text": {
                        "EN": [
                            "eastern",
                            "pa"
                        ],
                        "FA": [
                            "eastern",
                            "pa"
                        ]
                    }
                },
                {
                    "id": "AST_LAYOUT_ATTRIBUTE_VALUE_TYPE_QU",
                    "generate_name": "QU",
                    "text": {
                        "EN": [
                            "quechua",
                            "qu"
                        ],
                        "FA": [
                            "quechua",
                            "qu"
                        ]
                    }
                },
                {
                    "id": "AST_LAYOUT_ATTRIBUTE_VALUE_TYPE_RM",
                    "generate_name": "RM",
                    "text": {
                        "EN": [
                            "romansh",
                            "rm"
                        ],
                        "FA": [
                            "romansh",
                            "rm"
                        ]
                    }
                },
                {
                    "id": "AST_LAYOUT_ATTRIBUTE_VALUE_TYPE_RO",
                    "generate_name": "RO",
                    "text": {
                        "EN": [
                            "romanian",
                            "ro"
                        ],
                        "FA": [
                            "romanian",
                            "ro"
                        ]
                    }
                },
                {
                    "id": "AST_LAYOUT_ATTRIBUTE_VALUE_TYPE_RU",
                    "generate_name": "RU",
                    "text": {
                        "EN": [
                            "russian",
                            "ru"
                        ],
                        "FA": [
                            "russian",
                            "ru"
                        ]
                    }
                },
                {
                    "id": "AST_LAYOUT_ATTRIBUTE_VALUE_TYPE_SE",
                    "generate_name": "SE",
                    "text": {
                        "EN": [
                            "sami",
                            "se"
                        ],
                        "FA": [
                            "sami",
                            "se"
                        ]
                    }
                },
                {
                    "id": "AST_LAYOUT_ATTRIBUTE_VALUE_TYPE_SM",
                    "generate_name": "SM",
                    "text": {
                        "EN": [
                            "samoan",
                            "sm"
                        ],
                        "FA": [
                            "samoan",
                            "sm"
                        ]
                    }
                },
                {
                    "id": "AST_LAYOUT_ATTRIBUTE_VALUE_TYPE_SG",
                    "generate_name": "SG",
                    "text": {
                        "EN": [
                            "sango",
                            "sg"
                        ],
                        "FA": [
                            "sango",
                            "sg"
                        ]
                    }
                },
                {
                    "id": "AST_LAYOUT_ATTRIBUTE_VALUE_TYPE_SA",
                    "generate_name": "SA",
                    "text": {
                        "EN": [
                            "sanskrit",
                            "sa"
                        ],
                        "FA": [
                            "sanskrit",
                            "sa"
                        ]
                    }
                },
                {
                    "id": "AST_LAYOUT_ATTRIBUTE_VALUE_TYPE_SR",
                    "generate_name": "SR",
                    "text": {
                        "EN": [
                            "serbian",
                            "sr"
                        ],
                        "FA": [
                            "serbian",
                            "sr"
                        ]
                    }
                },
                {
                    "id": "AST_LAYOUT_ATTRIBUTE_VALUE_TYPE_SH",
                    "generate_name": "SH",
                    "text": {
                        "EN": [
                            "serbo-croatian",
                            "sh"
                        ],
                        "FA": [
                            "serbo-croatian",
                            "sh"
                        ]
                    }
                },
                {
                    "id": "AST_LAYOUT_ATTRIBUTE_VALUE_TYPE_ST",
                    "generate_name": "ST",
                    "text": {
                        "EN": [
                            "sesotho",
                            "st"
                        ],
                        "FA": [
                            "sesotho",
                            "st"
                        ]
                    }
                },
                {
                    "id": "AST_LAYOUT_ATTRIBUTE_VALUE_TYPE_TN",
                    "generate_name": "TN",
                    "text": {
                        "EN": [
                            "setswana",
                            "tn"
                        ],
                        "FA": [
                            "setswana",
                            "tn"
                        ]
                    }
                },
                {
                    "id": "AST_LAYOUT_ATTRIBUTE_VALUE_TYPE_SN",
                    "generate_name": "SN",
                    "text": {
                        "EN": [
                            "shona",
                            "sn"
                        ],
                        "FA": [
                            "shona",
                            "sn"
                        ]
                    }
                },
                {
                    "id": "AST_LAYOUT_ATTRIBUTE_VALUE_TYPE_II",
                    "generate_name": "II",
                    "text": {
                        "EN": [
                            "sichuan yi",
                            "ii"
                        ],
                        "FA": [
                            "sichuan yi",
                            "ii"
                        ]
                    }
                },
                {
                    "id": "AST_LAYOUT_ATTRIBUTE_VALUE_TYPE_SD",
                    "generate_name": "SD",
                    "text": {
                        "EN": [
                            "sindhi",
                            "sd"
                        ],
                        "FA": [
                            "sindhi",
                            "sd"
                        ]
                    }
                },
                {
                    "id": "AST_LAYOUT_ATTRIBUTE_VALUE_TYPE_SI",
                    "generate_name": "SI",
                    "text": {
                        "EN": [
                            "sinhalese",
                            "si"
                        ],
                        "FA": [
                            "sinhalese",
                            "si"
                        ]
                    }
                },
                {
                    "id": "AST_LAYOUT_ATTRIBUTE_VALUE_TYPE_SS",
                    "generate_name": "SS",
                    "text": {
                        "EN": [
                            "siswati",
                            "ss"
                        ],
                        "FA": [
                            "siswati",
                            "ss"
                        ]
                    }
                },
                {
                    "id": "AST_LAYOUT_ATTRIBUTE_VALUE_TYPE_SK",
                    "generate_name": "SK",
                    "text": {
                        "EN": [
                            "slovak",
                            "sk"
                        ],
                        "FA": [
                            "slovak",
                            "sk"
                        ]
                    }
                },
                {
                    "id": "AST_LAYOUT_ATTRIBUTE_VALUE_TYPE_SL",
                    "generate_name": "SL",
                    "text": {
                        "EN": [
                            "slovenian",
                            "sl"
                        ],
                        "FA": [
                            "slovenian",
                            "sl"
                        ]
                    }
                },
                {
                    "id": "AST_LAYOUT_ATTRIBUTE_VALUE_TYPE_SO",
                    "generate_name": "SO",
                    "text": {
                        "EN": [
                            "somali",
                            "so"
                        ],
                        "FA": [
                            "somali",
                            "so"
                        ]
                    }
                },
                {
                    "id": "AST_LAYOUT_ATTRIBUTE_VALUE_TYPE_NR",
                    "generate_name": "NR",
                    "text": {
                        "EN": [
                            "southern ndebele",
                            "nr"
                        ],
                        "FA": [
                            "southern ndebele",
                            "nr"
                        ]
                    }
                },
                {
                    "id": "AST_LAYOUT_ATTRIBUTE_VALUE_TYPE_ES",
                    "generate_name": "ES",
                    "text": {
                        "EN": [
                            "spanish",
                            "es"
                        ],
                        "FA": [
                            "spanish",
                            "es"
                        ]
                    }
                },
                {
                    "id": "AST_LAYOUT_ATTRIBUTE_VALUE_TYPE_SU",
                    "generate_name": "SU",
                    "text": {
                        "EN": [
                            "sundanese",
                            "su"
                        ],
                        "FA": [
                            "sundanese",
                            "su"
                        ]
                    }
                },
                {
                    "id": "AST_LAYOUT_ATTRIBUTE_VALUE_TYPE_SW",
                    "generate_name": "SW",
                    "text": {
                        "EN": [
                            "swahili",
                            "sw"
                        ],
                        "FA": [
                            "swahili",
                            "sw"
                        ]
                    }
                },
                {
                    "id": "AST_LAYOUT_ATTRIBUTE_VALUE_TYPE_SW",
                    "generate_name": "SW",
                    "text": {
                        "EN": [
                            "kiswahili",
                            "sw"
                        ],
                        "FA": [
                            "kiswahili",
                            "sw"
                        ]
                    }
                },
                {
                    "id": "AST_LAYOUT_ATTRIBUTE_VALUE_TYPE_SS",
                    "generate_name": "SS",
                    "text": {
                        "EN": [
                            "swati",
                            "ss"
                        ],
                        "FA": [
                            "swati",
                            "ss"
                        ]
                    }
                },
                {
                    "id": "AST_LAYOUT_ATTRIBUTE_VALUE_TYPE_SV",
                    "generate_name": "SV",
                    "text": {
                        "EN": [
                            "swedish",
                            "sv"
                        ],
                        "FA": [
                            "swedish",
                            "sv"
                        ]
                    }
                },
                {
                    "id": "AST_LAYOUT_ATTRIBUTE_VALUE_TYPE_TL",
                    "generate_name": "TL",
                    "text": {
                        "EN": [
                            "tagalog",
                            "tl"
                        ],
                        "FA": [
                            "tagalog",
                            "tl"
                        ]
                    }
                },
                {
                    "id": "AST_LAYOUT_ATTRIBUTE_VALUE_TYPE_TY",
                    "generate_name": "TY",
                    "text": {
                        "EN": [
                            "tahitian",
                            "ty"
                        ],
                        "FA": [
                            "tahitian",
                            "ty"
                        ]
                    }
                },
                {
                    "id": "AST_LAYOUT_ATTRIBUTE_VALUE_TYPE_TG",
                    "generate_name": "TG",
                    "text": {
                        "EN": [
                            "tajik",
                            "tg"
                        ],
                        "FA": [
                            "tajik",
                            "tg"
                        ]
                    }
                },
                {
                    "id": "AST_LAYOUT_ATTRIBUTE_VALUE_TYPE_TA",
                    "generate_name": "TA",
                    "text": {
                        "EN": [
                            "tamil",
                            "ta"
                        ],
                        "FA": [
                            "tamil",
                            "ta"
                        ]
                    }
                },
                {
                    "id": "AST_LAYOUT_ATTRIBUTE_VALUE_TYPE_TT",
                    "generate_name": "TT",
                    "text": {
                        "EN": [
                            "tatar",
                            "tt"
                        ],
                        "FA": [
                            "tatar",
                            "tt"
                        ]
                    }
                },
                {
                    "id": "AST_LAYOUT_ATTRIBUTE_VALUE_TYPE_TE",
                    "generate_name": "TE",
                    "text": {
                        "EN": [
                            "telugu",
                            "te"
                        ],
                        "FA": [
                            "telugu",
                            "te"
                        ]
                    }
                },
                {
                    "id": "AST_LAYOUT_ATTRIBUTE_VALUE_TYPE_TH",
                    "generate_name": "TH",
                    "text": {
                        "EN": [
                            "thai",
                            "th"
                        ],
                        "FA": [
                            "thai",
                            "th"
                        ]
                    }
                },
                {
                    "id": "AST_LAYOUT_ATTRIBUTE_VALUE_TYPE_BO",
                    "generate_name": "BO",
                    "text": {
                        "EN": [
                            "tibetan",
                            "bo"
                        ],
                        "FA": [
                            "tibetan",
                            "bo"
                        ]
                    }
                },
                {
                    "id": "AST_LAYOUT_ATTRIBUTE_VALUE_TYPE_TI",
                    "generate_name": "TI",
                    "text": {
                        "EN": [
                            "tigrinya",
                            "ti"
                        ],
                        "FA": [
                            "tigrinya",
                            "ti"
                        ]
                    }
                },
                {
                    "id": "AST_LAYOUT_ATTRIBUTE_VALUE_TYPE_TO",
                    "generate_name": "TO",
                    "text": {
                        "EN": [
                            "tonga",
                            "to"
                        ],
                        "FA": [
                            "tonga",
                            "to"
                        ]
                    }
                },
                {
                    "id": "AST_LAYOUT_ATTRIBUTE_VALUE_TYPE_TS",
                    "generate_name": "TS",
                    "text": {
                        "EN": [
                            "tsonga",
                            "ts"
                        ],
                        "FA": [
                            "tsonga",
                            "ts"
                        ]
                    }
                },
                {
                    "id": "AST_LAYOUT_ATTRIBUTE_VALUE_TYPE_TR",
                    "generate_name": "TR",
                    "text": {
                        "EN": [
                            "turkish",
                            "tr"
                        ],
                        "FA": [
                            "turkish",
                            "tr"
                        ]
                    }
                },
                {
                    "id": "AST_LAYOUT_ATTRIBUTE_VALUE_TYPE_TK",
                    "generate_name": "TK",
                    "text": {
                        "EN": [
                            "turkmen",
                            "tk"
                        ],
                        "FA": [
                            "turkmen",
                            "tk"
                        ]
                    }
                },
                {
                    "id": "AST_LAYOUT_ATTRIBUTE_VALUE_TYPE_TW",
                    "generate_name": "TW",
                    "text": {
                        "EN": [
                            "twi",
                            "tw"
                        ],
                        "FA": [
                            "twi",
                            "tw"
                        ]
                    }
                },
                {
                    "id": "AST_LAYOUT_ATTRIBUTE_VALUE_TYPE_UG",
                    "generate_name": "UG",
                    "text": {
                        "EN": [
                            "uyghur",
                            "ug"
                        ],
                        "FA": [
                            "uyghur",
                            "ug"
                        ]
                    }
                },
                {
                    "id": "AST_LAYOUT_ATTRIBUTE_VALUE_TYPE_UK",
                    "generate_name": "UK",
                    "text": {
                        "EN": [
                            "ukrainian",
                            "uk"
                        ],
                        "FA": [
                            "ukrainian",
                            "uk"
                        ]
                    }
                },
                {
                    "id": "AST_LAYOUT_ATTRIBUTE_VALUE_TYPE_UR",
                    "generate_name": "UR",
                    "text": {
                        "EN": [
                            "urdu",
                            "ur"
                        ],
                        "FA": [
                            "urdu",
                            "ur"
                        ]
                    }
                },
                {
                    "id": "AST_LAYOUT_ATTRIBUTE_VALUE_TYPE_UZ",
                    "generate_name": "UZ",
                    "text": {
                        "EN": [
                            "uzbek",
                            "uz"
                        ],
                        "FA": [
                            "uzbek",
                            "uz"
                        ]
                    }
                },
                {
                    "id": "AST_LAYOUT_ATTRIBUTE_VALUE_TYPE_VE",
                    "generate_name": "VE",
                    "text": {
                        "EN": [
                            "venda",
                            "ve"
                        ],
                        "FA": [
                            "venda",
                            "ve"
                        ]
                    }
                },
                {
                    "id": "AST_LAYOUT_ATTRIBUTE_VALUE_TYPE_VI",
                    "generate_name": "VI",
                    "text": {
                        "EN": [
                            "vietnamese",
                            "vi"
                        ],
                        "FA": [
                            "vietnamese",
                            "vi"
                        ]
                    }
                },
                {
                    "id": "AST_LAYOUT_ATTRIBUTE_VALUE_TYPE_VO",
                    "generate_name": "VO",
                    "text": {
                        "EN": [
                            "volapük",
                            "vo"
                        ],
                        "FA": [
                            "volapük",
                            "vo"
                        ]
                    }
                },
                {
                    "id": "AST_LAYOUT_ATTRIBUTE_VALUE_TYPE_WA",
                    "generate_name": "WA",
                    "text": {
                        "EN": [
                            "wallon",
                            "wa"
                        ],
                        "FA": [
                            "wallon",
                            "wa"
                        ]
                    }
                },
                {
                    "id": "AST_LAYOUT_ATTRIBUTE_VALUE_TYPE_CY",
                    "generate_name": "CY",
                    "text": {
                        "EN": [
                            "welsh",
                            "cy"
                        ],
                        "FA": [
                            "welsh",
                            "cy"
                        ]
                    }
                },
                {
                    "id": "AST_LAYOUT_ATTRIBUTE_VALUE_TYPE_WO",
                    "generate_name": "WO",
                    "text": {
                        "EN": [
                            "wolof",
                            "wo"
                        ],
                        "FA": [
                            "wolof",
                            "wo"
                        ]
                    }
                },
                {
                    "id": "AST_LAYOUT_ATTRIBUTE_VALUE_TYPE_FY",
                    "generate_name": "FY",
                    "text": {
                        "EN": [
                            "western frisian",
                            "fy"
                        ],
                        "FA": [
                            "western frisian",
                            "fy"
                        ]
                    }
                },
                {
                    "id": "AST_LAYOUT_ATTRIBUTE_VALUE_TYPE_XH",
                    "generate_name": "XH",
                    "text": {
                        "EN": [
                            "xhosa",
                            "xh"
                        ],
                        "FA": [
                            "xhosa",
                            "xh"
                        ]
                    }
                },
                {
                    "id": "AST_LAYOUT_ATTRIBUTE_VALUE_TYPE_YI",
                    "generate_name": "YI",
                    "text": {
                        "EN": [
                            "yiddish",
                            "yi"
                        ],
                        "FA": [
                            "yiddish",
                            "yi"
                        ]
                    }
                },
                {
                    "id": "AST_LAYOUT_ATTRIBUTE_VALUE_TYPE_JI",
                    "generate_name": "JI",
                    "text": {
                        "EN": [
                            "yiddish",
                            "ji"
                        ],
                        "FA": [
                            "yiddish",
                            "ji"
                        ]
                    }
                },
                {
                    "id": "AST_LAYOUT_ATTRIBUTE_VALUE_TYPE_YO",
                    "generate_name": "YO",
                    "text": {
                        "EN": [
                            "yoruba",
                            "yo"
                        ],
                        "FA": [
                            "yoruba",
                            "yo"
                        ]
                    }
                },
                {
                    "id": "AST_LAYOUT_ATTRIBUTE_VALUE_TYPE_ZA",
                    "generate_name": "ZA",
                    "text": {
                        "EN": [
                            "zhuang",
                            "za"
                        ],
                        "FA": [
                            "zhuang",
                            "za"
                        ]
                    }
                },
                {
                    "id": "AST_LAYOUT_ATTRIBUTE_VALUE_TYPE_ZA",
                    "generate_name": "ZA",
                    "text": {
                        "EN": [
                            "chuang",
                            "za"
                        ],
                        "FA": [
                            "chuang",
                            "za"
                        ]
                    }
                },
                {
                    "id": "AST_LAYOUT_ATTRIBUTE_VALUE_TYPE_ZU",
                    "generate_name": "ZU",
                    "text": {
                        "EN": [
                            "zulu",
                            "zu"
                        ],
                        "FA": [
                            "zulu",
                            "zu"
                        ]
                    }
                }
            ]
        }
    ]
}
